vqt/__init__.py
vqt/helpers.py
vqt/vqt.py
vqt-0.1.3.dist-info/LICENSE.md
vqt-0.1.3.dist-info/METADATA
vqt-0.1.3.dist-info/WHEEL
vqt-0.1.3.dist-info/top_level.txt
vqt-0.1.3.dist-info/RECORD
