Metadata-Version: 2.1
Name: vqt
Version: 0.1.3
Summary: Variable Q-Transform with PyTorch backend
Home-page: https://github.com/RichieHakim/vqt
Author: Richard Hakim
License: LICENSE
Keywords: neuroscience,neuroimaging,machine learning,deep learning
License-File: LICENSE.md
Requires-Dist: matplotlib
Requires-Dist: numpy
Requires-Dist: scipy
Requires-Dist: tqdm
Requires-Dist: torch
Requires-Dist: pytest
Requires-Dist: hypothesis
